longbow/__init__.py
longbow/__main__.py
longbow/meta.py
longbow/annotate/__init__.py
longbow/annotate/command.py
longbow/convert/__init__.py
longbow/convert/command.py
longbow/correct/__init__.py
longbow/correct/command.py
longbow/demultiplex/__init__.py
longbow/demultiplex/command.py
longbow/extract/__init__.py
longbow/extract/command.py
longbow/filter/__init__.py
longbow/filter/command.py
longbow/inspect/__init__.py
longbow/inspect/command.py
longbow/model/__init__.py
longbow/model/command.py
longbow/pad/__init__.py
longbow/pad/command.py
longbow/peek/__init__.py
longbow/peek/command.py
longbow/scsplit/__init__.py
longbow/scsplit/command.py
longbow/segment/__init__.py
longbow/segment/command.py
longbow/sift/__init__.py
longbow/sift/command.py
longbow/stats/__init__.py
longbow/stats/command.py
longbow/tagfix/__init__.py
longbow/tagfix/command.py
longbow/train/__init__.py
longbow/train/command.py
longbow/utils/bam_utils.py
longbow/utils/barcode_utils.py
longbow/utils/cli_utils.py
longbow/utils/constants.py
longbow/utils/model.py
longbow/utils/plot_utils.py
maslongbow-0.5.37.dist-info/LICENSE
maslongbow-0.5.37.dist-info/METADATA
maslongbow-0.5.37.dist-info/WHEEL
maslongbow-0.5.37.dist-info/entry_points.txt
maslongbow-0.5.37.dist-info/top_level.txt
maslongbow-0.5.37.dist-info/RECORD
