Metadata-Version: 2.1
Name: maslongbow
Version: 0.5.37
Summary: Annotation and segmentation of MAS-seq data
Home-page: https://broadinstitute.github.io/longbow/
Author: Kiran V Garimella, Jonn Smith
Author-email: kiran@broadinstitute.org, jonn@broadinstitute.org
License: BSD 3-Clause
Platform: UNKNOWN
Classifier: Development Status :: 3 - Alpha
Classifier: Intended Audience :: Science/Research
Classifier: License :: OSI Approved :: BSD License
Classifier: Natural Language :: English
Classifier: Operating System :: OS Independent
Classifier: Programming Language :: Python :: 3.6
Classifier: Programming Language :: Python :: 3.7
Classifier: Programming Language :: Python :: 3.8
Classifier: Programming Language :: Python :: Implementation :: CPython
Requires-Python: >=3.6, <=3.7.9
Requires-Dist: click
Requires-Dist: click-log
Requires-Dist: construct
Requires-Dist: cython
Requires-Dist: isort (==4.3.21)
Requires-Dist: matplotlib
Requires-Dist: mypy
Requires-Dist: numpy
Requires-Dist: pandas
Requires-Dist: pathos
Requires-Dist: pomegranate
Requires-Dist: progress
Requires-Dist: pysam (==0.19.1)
Requires-Dist: ssw (==0.4.1)
Requires-Dist: symspellpy
Requires-Dist: tqdm
